similar_sounding_words.py
similar_sounding_words-0.1.2.dist-info/LICENSE.txt
similar_sounding_words-0.1.2.dist-info/METADATA
similar_sounding_words-0.1.2.dist-info/WHEEL
similar_sounding_words-0.1.2.dist-info/top_level.txt
similar_sounding_words-0.1.2.dist-info/RECORD
