Metadata-Version: 2.1
Name: similar-sounding-words
Version: 0.1.2
Summary: A list of similar sounding words to help disambiguate voice coding
Home-page: https://github.com/dusty-phillips/similar-sounding-words
License: UNKNOWN
Platform: UNKNOWN
Classifier: Programming Language :: Python :: 3
Classifier: License :: OSI Approved :: MIT License
Classifier: Operating System :: OS Independent
Classifier: Intended Audience :: Developers
Requires-Python: >=3.8
